MANIFEST.in
Makefile
README
setup.py
test/__init__.py
test/test_simplerizer_yaml.py
tiddlywebplugins/__init__.py
tiddlywebplugins/simplerizer.py
tiddlywebplugins.simplerizer.egg-info/PKG-INFO
tiddlywebplugins.simplerizer.egg-info/SOURCES.txt
tiddlywebplugins.simplerizer.egg-info/dependency_links.txt
tiddlywebplugins.simplerizer.egg-info/namespace_packages.txt
tiddlywebplugins.simplerizer.egg-info/requires.txt
tiddlywebplugins.simplerizer.egg-info/top_level.txt