Metadata-Version: 1.0
Name: tiddlywebplugins.simplerizer
Version: 0.1
Summary: TiddlyWeb plugin to simplify the development of serializers.
Home-page: http://pypi.python.org/pypi/tiddlywebplugins.simplerizer
Author: Paul Downey
Author-email: paul.downey@whatfettle.com
License: UNKNOWN
Platform: Posix; MacOS X; Windows
